pypywhois/_1_query.py
pypywhois/_2_parse.py
pypywhois/_3_adjust.py
pypywhois/__init__.py
pypywhois/exceptions.py
pypywhois/tld_regexpr.py
pypywhois/data/public_suffix_list.dat
pypywhois-1.2.dist-info/METADATA
pypywhois-1.2.dist-info/WHEEL
pypywhois-1.2.dist-info/license
pypywhois-1.2.dist-info/top_level.txt
pypywhois-1.2.dist-info/RECORD
